tft/phoebe/__init__.py
tft/phoebe/exporter_arbitrary.py
tft/phoebe/exporter_aws.py
tft/phoebe/exporter_aws.yaml.example
tft/phoebe/exporter_beaker.yaml.example~
tft/phoebe/exporter_jenkins.py
tft/phoebe/exporter_jenkins.yaml.example
tft/phoebe/exporter_openstack.py
tft/phoebe/exporter_openstack.py~
tft/phoebe/exporter_openstack.yaml.example
tft_phoebe-0.0.13.dist-info/entry_points.txt
tft_phoebe-0.0.13.dist-info/LICENSE
tft_phoebe-0.0.13.dist-info/WHEEL
tft_phoebe-0.0.13.dist-info/METADATA
tft_phoebe-0.0.13.dist-info/RECORD
